blabber/__init__.py
blabber/data/mult.txt
blabber/data/open.txt
blabber/data/rather.txt
blabber/data/yesno.txt
blabber-0.1.1.data/data/mult.txt
blabber-0.1.1.data/data/open.txt
blabber-0.1.1.data/data/rather.txt
blabber-0.1.1.data/data/yesno.txt
blabber-0.1.1.dist-info/LICENSE
blabber-0.1.1.dist-info/WHEEL
blabber-0.1.1.dist-info/METADATA
blabber-0.1.1.dist-info/RECORD
