Metadata-Version: 2.1
Name: blabber
Version: 0.1.1
Summary: Blabber generates conversation starters.
Author-email: Ben Soyka <bensoyka@icloud.com>
Requires-Python: ~=3.7
Classifier: Development Status :: 2 - Pre-Alpha
Classifier: Intended Audience :: Developers
Classifier: Natural Language :: English
Classifier: License :: OSI Approved :: MIT License
Classifier: Programming Language :: Python
Classifier: Programming Language :: Python :: 3
Classifier: Programming Language :: Python :: 3.7
Classifier: Programming Language :: Python :: 3.8
Classifier: Programming Language :: Python :: 3.9
Classifier: Programming Language :: Python :: 3.10
Project-URL: Changelog, https://github.com/bsoyka/blabber/releases
Project-URL: Source, https://github.com/bsoyka/blabber
